mtmcxstrtg/__init__.py
mtmcxstrtg/account.py
mtmcxstrtg/config.py
mtmcxstrtg/flow.py
mtmcxstrtg/util.py
mtmcxstrtg/strategy/__init__.py
mtmcxstrtg/strategy/cta_deviation_signal_strategy.py
mtmcxstrtg-1.0.9.data/scripts/run.py
mtmcxstrtg-1.0.9.dist-info/METADATA
mtmcxstrtg-1.0.9.dist-info/WHEEL
mtmcxstrtg-1.0.9.dist-info/top_level.txt
mtmcxstrtg-1.0.9.dist-info/RECORD
